README.txt
setup.cfg
setup.py
docs/HISTORY.txt
docs/INSTALL.txt
docs/LICENSE.GPL
docs/LICENSE.txt
easyshop/__init__.py
easyshop.shop.egg-info/PKG-INFO
easyshop.shop.egg-info/SOURCES.txt
easyshop.shop.egg-info/dependency_links.txt
easyshop.shop.egg-info/entry_points.txt
easyshop.shop.egg-info/namespace_packages.txt
easyshop.shop.egg-info/not-zip-safe
easyshop.shop.egg-info/requires.txt
easyshop.shop.egg-info/top_level.txt
easyshop/shop/__init__.py
easyshop/shop/configure.zcml
easyshop/shop/profiles.zcml
easyshop/shop/adapters/__init__.py
easyshop/shop/adapters/configure.zcml
easyshop/shop/adapters/currency_management.py
easyshop/shop/adapters/image_conversion.py
easyshop/shop/adapters/image_management.py
easyshop/shop/adapters/mail_addresses.py
easyshop/shop/adapters/shop_management.py
easyshop/shop/adapters/validity.py
easyshop/shop/browser/__init__.py
easyshop/shop/browser/configure.zcml
easyshop/shop/browser/sitemap.pt
easyshop/shop/browser/sitemap.py
easyshop/shop/browser/admin/__init__.py
easyshop/shop/browser/admin/configure.zcml
easyshop/shop/browser/admin/export.py
easyshop/shop/browser/admin/migrate.py
easyshop/shop/browser/admin/test_environment.py
easyshop/shop/content/__init__.py
easyshop/shop/content/shop.py
easyshop/shop/docs/__init__.py
easyshop/shop/docs/test_add_product.txt
easyshop/shop/docs/test_category_criteria.txt
easyshop/shop/docs/test_checkout_1.txt
easyshop/shop/docs/test_customer_manages_addressebook.txt
easyshop/shop/docs/test_payment_methods.txt
easyshop/shop/docs/test_payment_price.txt
easyshop/shop/docs/test_shipping_method.txt
easyshop/shop/docs/test_shipping_price.txt
easyshop/shop/migrations/__init__.py
easyshop/shop/migrations/configure.zcml
easyshop/shop/migrations/formatter.py
easyshop/shop/portlets/__init__.py
easyshop/shop/portlets/admin.pt
easyshop/shop/portlets/admin.py
easyshop/shop/portlets/configure.zcml
easyshop/shop/profiles/__init__.py
easyshop/shop/profiles/default/catalog.xml
easyshop/shop/profiles/default/cssregistry.xml
easyshop/shop/profiles/default/factorytool.xml
easyshop/shop/profiles/default/jsregistry.xml
easyshop/shop/profiles/default/portlets.xml
easyshop/shop/profiles/default/propertiestool.xml
easyshop/shop/profiles/default/skins.xml
easyshop/shop/profiles/default/types.xml
